hyperfetch/__init__.py
hyperfetch/alg_samplers.py
hyperfetch/auth_connection.py
hyperfetch/callbacks.py
hyperfetch/manager.py
hyperfetch/tuning.py
hyperfetch/util.py
siste_test-0.1.0.dist-info/LICENSE
siste_test-0.1.0.dist-info/METADATA
siste_test-0.1.0.dist-info/WHEEL
siste_test-0.1.0.dist-info/entry_points.txt
siste_test-0.1.0.dist-info/top_level.txt
siste_test-0.1.0.dist-info/RECORD
