Metadata-Version: 2.1
Name: siste-test
Version: 0.1.0
Summary: HyperFetch. A tool to optimize and fetch hyperparameters for your reinforcement learning application.
Author-email: Karoline Sund Wahl <karolies.wahl@gmail.com>
License: Copyright 2023 Karoline Sund Wahl
Project-URL: Backend, https://github.com/karolisw/hyperFetch
Project-URL: Website, https://github.com/karolisw/hyperFetch/tree/frontend
Project-URL: Source, https://github.com/karolisw/hyperFetch
Keywords: reinforcement learning,hyperparameters,replication
Classifier: Development Status :: 3 - Alpha
Classifier: Intended Audience :: Developers
Classifier: License :: OSI Approved :: BSD License
Classifier: Operating System :: Microsoft :: Windows :: Windows 11
Classifier: Programming Language :: Python :: 3.9
Classifier: Programming Language :: Python :: 3.10
Classifier: Framework :: FastAPI
Requires-Python: >=3.9
License-File: LICENSE
Requires-Dist: torch (==1.13.1)
Requires-Dist: torchvision (==0.14.1)
Requires-Dist: torchaudio (==0.13.1)
Requires-Dist: numpy (==1.24.2)
Requires-Dist: swig (==4.1.1)
Requires-Dist: codecarbon (>=2.1.3)
Requires-Dist: databases (==0.7.0)
Requires-Dist: fastapi (>=0.89.1)
Requires-Dist: optuna (==3.1.1)
Requires-Dist: gym (==0.21.0)
Requires-Dist: pymongo (==4.3.3)
Requires-Dist: motor (==3.1.2)
Requires-Dist: motor-stubs (==1.7.1)
Requires-Dist: mypy (==1.1.1)
Requires-Dist: pandas (==1.5.3)
Requires-Dist: pyaml (==21.10.1)
Requires-Dist: pydantic (>=1.10.4)
Requires-Dist: SQLAlchemy (==1.4.47)
Requires-Dist: stable-baselines3 (==1.7.0)
Requires-Dist: starlette (>=0.22.0)
Requires-Dist: uvicorn (>=0.20.0)
Requires-Dist: absl-py (==1.4.0)
Requires-Dist: alembic (==1.9.3)
Requires-Dist: anyio (==3.6.2)
Requires-Dist: arrow (==1.2.3)
Requires-Dist: attrs (==22.2.0)
Requires-Dist: bcrypt (==4.0.1)
Requires-Dist: box2d-py (==2.3.5)
Requires-Dist: cachetools (==5.3.0)
Requires-Dist: certifi (==2022.12.7)
Requires-Dist: chardet (==5.1.0)
Requires-Dist: charset-normalizer (==3.0.1)
Requires-Dist: click (==8.1.3)
Requires-Dist: cloudpickle (==1.6.0)
Requires-Dist: cmaes (==0.9.1)
Requires-Dist: colorama (==0.4.6)
Requires-Dist: colorlog (==6.7.0)
Requires-Dist: contourpy (==1.0.7)
Requires-Dist: cycler (==0.11.0)
Requires-Dist: DataProperty (==0.55.0)
Requires-Dist: dnspython (==2.3.0)
Requires-Dist: email-validator (==1.3.1)
Requires-Dist: exceptiongroup (==1.1.1)
Requires-Dist: filelock
Requires-Dist: fonttools (==4.38.0)
Requires-Dist: fuzzywuzzy (==0.18.0)
Requires-Dist: google-auth
Requires-Dist: google-auth-oauthlib (==0.4.6)
Requires-Dist: greenlet (==2.0.2)
Requires-Dist: grpcio (==1.51.1)
Requires-Dist: gym-notices (==0.0.8)
Requires-Dist: gymnasium-notices (==0.0.1)
Requires-Dist: h11 (==0.14.0)
Requires-Dist: httpcore (==0.16.3)
Requires-Dist: httptools (==0.5.0)
Requires-Dist: httpx (==0.23.3)
Requires-Dist: huggingface-hub (==0.12.0)
Requires-Dist: huggingface-sb3 (==2.2.4)
Requires-Dist: idna (==3.4)
Requires-Dist: importlib-metadata (==4.13.0)
Requires-Dist: iniconfig (==2.0.0)
Requires-Dist: itsdangerous (==2.1.2)
Requires-Dist: jax-jumpy (==0.2.0)
Requires-Dist: Jinja2 (==3.1.2)
Requires-Dist: joblib (==1.2.0)
Requires-Dist: kiwisolver (==1.4.4)
Requires-Dist: Mako (==1.2.4)
Requires-Dist: Markdown (==3.4.1)
Requires-Dist: markdown-it-py (==2.2.0)
Requires-Dist: MarkupSafe (==2.1.2)
Requires-Dist: matplotlib (==3.6.3)
Requires-Dist: mbstrdecoder (==1.1.2)
Requires-Dist: mdurl (==0.1.2)
Requires-Dist: mypy-extensions (==1.0.0)
Requires-Dist: oauthlib (==3.2.2)
Requires-Dist: orjson (==3.8.5)
Requires-Dist: packaging (==23.0)
Requires-Dist: passlib (==1.7.4)
Requires-Dist: pathvalidate (==2.5.2)
Requires-Dist: Pillow (==9.4.0)
Requires-Dist: pluggy (==1.0.0)
Requires-Dist: protobuf (==3.20.3)
Requires-Dist: psutil (==5.9.4)
Requires-Dist: py-cpuinfo (==9.0.0)
Requires-Dist: pyasn1 (==0.4.8)
Requires-Dist: pyasn1-modules (==0.2.8)
Requires-Dist: pygame (==2.1.0)
Requires-Dist: pyglet (==1.5.27)
Requires-Dist: Pygments (==2.14.0)
Requires-Dist: pynvml (==11.5.0)
Requires-Dist: PyOpenGL (==3.1.6)
Requires-Dist: pyparsing (==3.0.9)
Requires-Dist: pytablewriter (==0.64.2)
Requires-Dist: pytest (==7.2.2)
Requires-Dist: python-benedict
Requires-Dist: python-dateutil (==2.8.2)
Requires-Dist: python-dotenv (==0.21.1)
Requires-Dist: python-multipart (==0.0.5)
Requires-Dist: pytz (==2022.7.1)
Requires-Dist: PyYAML (==6.0)
Requires-Dist: requests (==2.28.2)
Requires-Dist: requests-oauthlib (==1.3.1)
Requires-Dist: rfc3986 (==1.5.0)
Requires-Dist: rich (==13.3.1)
Requires-Dist: rl-zoo3 (==1.7.0)
Requires-Dist: rsa (==4.9)
Requires-Dist: sb3-contrib (==1.7.0)
Requires-Dist: scikit-learn (==1.2.1)
Requires-Dist: scikit-optimize (==0.9.0)
Requires-Dist: scipy (==1.10.0)
Requires-Dist: six (==1.16.0)
Requires-Dist: sniffio (==1.3.0)
Requires-Dist: tabledata (==1.3.0)
Requires-Dist: tcolorpy (==0.1.2)
Requires-Dist: tensorboard (==2.11.2)
Requires-Dist: tensorboard-data-server (==0.6.1)
Requires-Dist: tensorboard-plugin-wit (==1.8.1)
Requires-Dist: threadpoolctl (==3.1.0)
Requires-Dist: tomli (==2.0.1)
Requires-Dist: tqdm (==4.64.1)
Requires-Dist: typepy (==1.3.0)
Requires-Dist: types-PyYAML (==6.0.12.8)
Requires-Dist: typing-extensions (==4.4.0)
Requires-Dist: ujson (==5.7.0)
Requires-Dist: urllib3 (==1.26.14)
Requires-Dist: wasabi (==1.1.1)
Requires-Dist: watchfiles (==0.18.1)
Requires-Dist: websockets (==10.4)
Requires-Dist: Werkzeug (>=2.2.3)
Requires-Dist: zipp (==3.12.1)
